up2ynab/__init__.py
up2ynab/clients/__init__.py
up2ynab/clients/up.py
up2ynab/clients/ynab.py
up2ynab/commands/__init__.py
up2ynab/commands/check.py
up2ynab/commands/transactions.py
up2ynab/util/__init__.py
up2ynab/util/http_error_handler.py
up2ynab/util/pretty_echo.py
up2ynab-0.1.0.dist-info/LICENSE.txt
up2ynab-0.1.0.dist-info/METADATA
up2ynab-0.1.0.dist-info/WHEEL
up2ynab-0.1.0.dist-info/entry_points.txt
up2ynab-0.1.0.dist-info/top_level.txt
up2ynab-0.1.0.dist-info/RECORD
