Metadata-Version: 2.1
Name: up2ynab
Version: 0.1.0
Summary: CLI for synchronising the Up neobank with YNAB
Home-page: https://github.com/lachholden/up2ynab
Author: Lachlan H
Author-email: lachlan.holden@gmail.com
License: MIT
Keywords: cli bank import sync YNAB Up
Platform: UNKNOWN
Classifier: Development Status :: 4 - Beta
Classifier: Environment :: Console
Classifier: License :: OSI Approved :: MIT License
Classifier: Natural Language :: English
Classifier: Operating System :: OS Independent
Classifier: Programming Language :: Python :: 3 :: Only
Classifier: Programming Language :: Python :: 3.8
Classifier: Topic :: Office/Business :: Financial
Classifier: Topic :: Utilities
Requires-Python: >=3
Requires-Dist: click
Requires-Dist: requests
